{"blog_index.md":"b8eeb6e5","blog_rust_array.md":"1c70ea76","blog_rust_entry.md":"4de26934","blog_rust_enum.md":"f3587e3e","blog_rust_expression.md":"20b8e55f","blog_rust_mode-match.md":"72d54c89","blog_rust_ownership.md":"8b0582ad","blog_rust_process-control.md":"ec08a4f7","blog_rust_slice.md":"447de4cb","blog_rust_string.md":"26d49730","blog_rust_struct.md":"c51b8521","blog_rust_tuple.md":"f7856197","blog_rust_variable.md":"7b41bd00","gallery_index.md":"fcbb5f23","index.md":"5be02443","note_index.md":"cfbca4b8"}
